l3wrapper/__init__.py
l3wrapper/classification.py
l3wrapper/dictionary.py
l3wrapper/l3wrapper.py
l3wrapper/validation.py
l3wrapper-0.7.0.dist-info/LICENSE
l3wrapper-0.7.0.dist-info/METADATA
l3wrapper-0.7.0.dist-info/WHEEL
l3wrapper-0.7.0.dist-info/top_level.txt
l3wrapper-0.7.0.dist-info/RECORD
