Metadata-Version: 2.1
Name: l3wrapper
Version: 0.7.0
Summary: A simple Python 3 wrapper around L3 binaries.
Home-page: https://github.com/g8a9/l3wrapper
Author: Giuseppe Attanasio
Author-email: giuseppe.attanasio@polito.it
License: MIT
Platform: UNKNOWN
Classifier: Development Status :: 4 - Beta
Classifier: License :: OSI Approved :: MIT License
Classifier: Programming Language :: Python
Classifier: Programming Language :: Python :: 3
Classifier: Programming Language :: Python :: 3.6
Classifier: Programming Language :: Python :: 3.7
Requires-Dist: numpy
Requires-Dist: scikit-learn
Requires-Dist: tqdm
Requires-Dist: requests
